juniordev/CEO/CEO.py
juniordev/CEO/__init__.py
juniordev/CEO/instructions.md
juniordev/CEO/tools/__init__.py
juniordev/Copywriter/Copywriter.py
juniordev/Copywriter/__init__.py
juniordev/Copywriter/instructions.md
juniordev/Copywriter/tools/__init__.py
juniordev/Designer/Designer.py
juniordev/Designer/__init__.py
juniordev/Designer/instructions.md
juniordev/Designer/tools/AnalyzeContent.py
juniordev/Designer/tools/__init__.py
juniordev/WebDeveloper/WebDeveloper.py
juniordev/WebDeveloper/__init__.py
juniordev/WebDeveloper/instructions.md
juniordev/WebDeveloper/tools/ChangeLines.py
juniordev/WebDeveloper/tools/CheckCurrentDir.py
juniordev/WebDeveloper/tools/DirectoryNavigator.py
juniordev/WebDeveloper/tools/FileReader.py
juniordev/WebDeveloper/tools/FileWriter.py
juniordev/WebDeveloper/tools/ListDir.py
juniordev/WebDeveloper/tools/RunCommand.py
juniordev/WebDeveloper/tools/__init__.py
juniordev/__init__.py
juniordev/agency.py
juniordev/agency_manifesto.md
juniordev-0.2.0.dist-info/METADATA
juniordev-0.2.0.dist-info/WHEEL
juniordev-0.2.0.dist-info/entry_points.txt
juniordev-0.2.0.dist-info/RECORD
