Metadata-Version: 2.1
Name: juniordev
Version: 0.2.0
Summary: 
Author: santoshdahal2016
Author-email: webtutor2016@gmail.com
Requires-Python: >=3.9,<4.0
Classifier: Programming Language :: Python :: 3
Classifier: Programming Language :: Python :: 3.9
Classifier: Programming Language :: Python :: 3.10
Classifier: Programming Language :: Python :: 3.11
Classifier: Programming Language :: Python :: 3.12
Requires-Dist: agency-swarm (>=0.2.6,<0.3.0)
Requires-Dist: selenium-stealth (>=1.0.6,<2.0.0)
Requires-Dist: webdriver-manager (>=4.0.2,<5.0.0)
